{
  "_comment": "Hand-maintained. See TURN1_RULES.md for the research and sources behind these entries - update that file first if a new rule era needs adding.",
  "2010": {
    "flip": "Winner Goes First",
    "rules": [
      { "label": "Supporters, Items, Stadium", "allowed": false },
      { "label": "Attack", "allowed": true }
    ]
  },
  "2012": {
    "flip": "Winner Goes First",
    "rules": [
      { "label": "Items, Supporters, Stadium", "allowed": true },
      { "label": "Attack", "allowed": true }
    ]
  },
  "2013": {
    "flip": "Winner Goes First",
    "rules": [
      { "label": "Items, Supporters, Stadium", "allowed": true },
      { "label": "Attack", "allowed": true }
    ]
  },
  "2014": {
    "flip": "Winner Chooses",
    "rules": [
      { "label": "Items, Supporters, Stadium", "allowed": true },
      { "label": "Attack", "allowed": false }
    ]
  },
  "2015": {
    "flip": "Winner Chooses",
    "rules": [
      { "label": "Items, Supporters, Stadium", "allowed": true },
      { "label": "Attack", "allowed": false }
    ]
  },
  "2016": {
    "flip": "Winner Chooses",
    "rules": [
      { "label": "Items, Supporters, Stadium", "allowed": true },
      { "label": "Attack", "allowed": false }
    ]
  },
  "2017": {
    "flip": "Winner Chooses",
    "rules": [
      { "label": "Items, Supporters, Stadium", "allowed": true },
      { "label": "Attack", "allowed": false }
    ]
  },
  "2017 NAIC": {
    "flip": "Winner Chooses",
    "rules": [
      { "label": "Items, Supporters, Stadium", "allowed": true },
      { "label": "Attack", "allowed": false }
    ]
  },
  "2018": {
    "flip": "Winner Chooses",
    "rules": [
      { "label": "Items, Supporters, Stadium", "allowed": true },
      { "label": "Attack", "allowed": false }
    ]
  },
  "2019": {
    "flip": "Winner Chooses",
    "rules": [
      { "label": "Items, Supporters, Stadium", "allowed": true },
      { "label": "Attack", "allowed": false }
    ]
  },
  "2020": {
    "flip": "Winner Chooses",
    "rules": [
      { "label": "Items, Stadium", "allowed": true },
      { "label": "Supporters", "allowed": false },
      { "label": "Attack", "allowed": false }
    ]
  },
  "2022": {
    "flip": "Winner Chooses",
    "rules": [
      { "label": "Items, Stadium", "allowed": true },
      { "label": "Supporters", "allowed": false },
      { "label": "Attack", "allowed": false }
    ]
  },
  "2023": {
    "flip": "Winner Chooses",
    "rules": [
      { "label": "Items, Stadium", "allowed": true },
      { "label": "Supporters", "allowed": false },
      { "label": "Attack", "allowed": false }
    ]
  },
  "2024": {
    "flip": "Winner Chooses",
    "rules": [
      { "label": "Items, Stadium", "allowed": true },
      { "label": "Supporters", "allowed": false },
      { "label": "Attack", "allowed": false }
    ]
  },
  "2025": {
    "flip": "Winner Chooses",
    "rules": [
      { "label": "Items, Stadium", "allowed": true },
      { "label": "Supporters", "allowed": false },
      { "label": "Attack", "allowed": false }
    ]
  }
}
